pan_iot_security_python-0.3.0.data/scripts/iotapi.py
paniot/__init__.py
paniot/mixin.py
paniot/v4_0aioapi.py
paniot/v4_0api.py
pan_iot_security_python-0.3.0.dist-info/LICENSE.txt
pan_iot_security_python-0.3.0.dist-info/METADATA
pan_iot_security_python-0.3.0.dist-info/WHEEL
pan_iot_security_python-0.3.0.dist-info/top_level.txt
pan_iot_security_python-0.3.0.dist-info/RECORD
