Metadata-Version: 2.1
Name: pan-iot-security-python
Version: 0.3.0
Summary: Python interface to the Palo Alto Networks IoT Security API
Home-page: https://github.com/PaloAltoNetworks/pan-iot-security-python
Author: Palo Alto Networks, Inc.
Author-email: devrel@paloaltonetworks.com
License: ISC
Classifier: Programming Language :: Python :: 3
Classifier: License :: OSI Approved :: ISC License (ISCL)
Requires-Python: >=3.8
License-File: LICENSE.txt
Requires-Dist: aiohttp (>=3.8.1)
Requires-Dist: requests (>=2.27.1)
